[
   {
      "id": "1179994655",
      "photo": "http://dummyimage.com/376x203.png/cc0000/ffffff",
      "guest_name": "Kata Garfit",
      "order_date": "2021-07-02 13:42:00",
      "check_in": "2021-01-25 22:23:49",
      "check_out": "2021-01-06 17:13:14",
      "request": "Separation of muscle (nontraumatic), forearm",
      "room_type": "Suite",
      "status": "In Progress",
      "price": "€167,33",
      "amenities": "LED tv, bath, late-checkout, sea view, city tour",
      "room_imgs": [{}, {}, {}],
      "room_desc": "In sagittis dui vel nisl. Duis ac nibh. Fusce lacus purus, aliquet at, feugiat non, pretium quis, lectus.\n\nSuspendisse potenti. In eleifend quam a odio. In hac habitasse platea dictumst.\n\nMaecenas ut massa quis augue luctus tincidunt. Nulla mollis molestie lorem. Quisque ut erat.\n\nCurabitur gravida nisi at nibh. In hac habitasse platea dictumst. Aliquam augue quam, sollicitudin vitae, consectetuer eget, rutrum at, lorem."
   },
   {
      "id": "1672499844",
      "photo": "http://dummyimage.com/216x382.png/ff4444/ffffff",
      "guest_name": "Michail Yellop",
      "order_date": "2021-06-04 23:49:27",
      "check_in": "2021-05-29 09:38:10",
      "check_out": "2021-05-16 19:15:40",
      "request": "Burn of cornea and conjunctival sac, unsp eye, sequela",
      "room_type": "Double",
      "status": "Check in",
      "price": "€221,09",
      "amenities": "LED tv, bath, late-checkout, sea view, city tour",
      "room_imgs": [{}, {}, {}, {}],
      "room_desc": "Morbi non lectus. Aliquam sit amet diam in magna bibendum imperdiet. Nullam orci pede, venenatis non, sodales sed, tincidunt eu, felis.\n\nFusce posuere felis sed lacus. Morbi sem mauris, laoreet ut, rhoncus aliquet, pulvinar sed, nisl. Nunc rhoncus dui vel sem.\n\nSed sagittis. Nam congue, risus semper porta volutpat, quam pede lobortis ligula, sit amet eleifend pede libero quis orci. Nullam molestie nibh in lectus.\n\nPellentesque at nulla. Suspendisse potenti. Cras in purus eu magna vulputate luctus."
   },
   {
      "id": "3289240207",
      "photo": "http://dummyimage.com/215x282.png/dddddd/000000",
      "guest_name": "Gerard Spennock",
      "order_date": "2021-12-13 16:57:20",
      "check_in": "2021-07-16 09:19:03",
      "check_out": "2021-07-01 22:02:38",
      "request": "Unsatisfactory restoration of tooth, unspecified",
      "room_type": "Suite",
      "status": "Check out",
      "price": "€168,29",
      "amenities": "LED tv, bath, late-checkout, sea view, city tour",
      "room_imgs": [{}, {}, {}],
      "room_desc": "Aenean fermentum. Donec ut mauris eget massa tempor convallis. Nulla neque libero, convallis eget, eleifend luctus, ultricies eu, nibh.\n\nQuisque id justo sit amet sapien dignissim vestibulum. Vestibulum ante ipsum primis in faucibus orci luctus et ultrices posuere cubilia Curae; Nulla dapibus dolor vel est. Donec odio justo, sollicitudin ut, suscipit a, feugiat et, eros.\n\nVestibulum ac est lacinia nisi venenatis tristique. Fusce congue, diam id ornare imperdiet, sapien urna pretium nisl, ut volutpat sapien arcu sed augue. Aliquam erat volutpat."
   },
   {
      "id": "2041497750",
      "photo": "http://dummyimage.com/203x388.png/5fa2dd/ffffff",
      "guest_name": "Jaymie Lepper",
      "order_date": "2021-04-23 11:51:42",
      "check_in": "2021-06-17 10:46:22",
      "check_out": "2021-08-01 12:18:16",
      "request": "Pasngr on bus inj in clsn w nonmtr vehicle nontraf, sequela",
      "room_type": "Single",
      "status": "Check in",
      "price": "€179,87",
      "amenities": "LED tv, bath, late-checkout, sea view, city tour",
      "room_imgs": [{}, {}, {}, {}, {}],
      "room_desc": "Integer tincidunt ante vel ipsum. Praesent blandit lacinia erat. Vestibulum sed magna at nunc commodo placerat.\n\nPraesent blandit. Nam nulla. Integer pede justo, lacinia eget, tincidunt eget, tempus vel, pede.\n\nMorbi porttitor lorem id ligula. Suspendisse ornare consequat lectus. In est risus, auctor sed, tristique in, tempus sit amet, sem.\n\nFusce consequat. Nulla nisl. Nunc nisl."
   },
   {
      "id": "0211190713",
      "photo": "http://dummyimage.com/222x319.png/5fa2dd/ffffff",
      "guest_name": "Will Saywood",
      "order_date": "2021-03-28 15:15:39",
      "check_in": "2021-05-11 20:19:34",
      "check_out": "2021-07-19 01:35:29",
      "request": "Neoplasm of uncertain behavior of oth digestive organs",
      "room_type": "Double",
      "status": "Check out",
      "price": "€166,53",
      "amenities": "LED tv, bath, late-checkout, sea view, city tour",
      "room_imgs": [{}, {}, {}, {}, {}],
      "room_desc": "Duis bibendum, felis sed interdum venenatis, turpis enim blandit mi, in porttitor pede justo eu massa. Donec dapibus. Duis at velit eu est congue elementum.\n\nIn hac habitasse platea dictumst. Morbi vestibulum, velit id pretium iaculis, diam erat fermentum justo, nec condimentum neque sapien placerat ante. Nulla justo."
   },
   {
      "id": "7539017120",
      "photo": "http://dummyimage.com/358x219.png/5fa2dd/ffffff",
      "guest_name": "Kelli Glasheen",
      "order_date": "2021-01-29 22:58:49",
      "check_in": "2021-03-03 17:23:07",
      "check_out": "2021-06-17 15:56:39",
      "request": "Pasngr in 3-whl mv inj pk-up truck, pk-up/van nontraf, init",
      "room_type": "Suite",
      "status": "In Progress",
      "price": "€386,46",
      "amenities": "LED tv, bath, late-checkout, sea view, city tour",
      "room_imgs": [{}, {}, {}, {}],
      "room_desc": "Sed sagittis. Nam congue, risus semper porta volutpat, quam pede lobortis ligula, sit amet eleifend pede libero quis orci. Nullam molestie nibh in lectus.\n\nPellentesque at nulla. Suspendisse potenti. Cras in purus eu magna vulputate luctus.\n\nCum sociis natoque penatibus et magnis dis parturient montes, nascetur ridiculus mus. Vivamus vestibulum sagittis sapien. Cum sociis natoque penatibus et magnis dis parturient montes, nascetur ridiculus mus.\n\nEtiam vel augue. Vestibulum rutrum rutrum neque. Aenean auctor gravida sem."
   },
   {
      "id": "1003642950",
      "photo": "http://dummyimage.com/318x363.png/ff4444/ffffff",
      "guest_name": "Barbaraanne Molen",
      "order_date": "2021-06-29 03:36:45",
      "check_in": "2021-07-24 21:38:21",
      "check_out": "2021-11-21 07:30:33",
      "request": "Spontaneous rupture of other tendons, shoulder",
      "room_type": "Double Superior",
      "status": "In Progress",
      "price": "€557,75",
      "amenities": "LED tv, bath, late-checkout, sea view, city tour",
      "room_imgs": [{}, {}, {}, {}, {}],
      "room_desc": "Vestibulum ac est lacinia nisi venenatis tristique. Fusce congue, diam id ornare imperdiet, sapien urna pretium nisl, ut volutpat sapien arcu sed augue. Aliquam erat volutpat.\n\nIn congue. Etiam justo. Etiam pretium iaculis justo.\n\nIn hac habitasse platea dictumst. Etiam faucibus cursus urna. Ut tellus."
   },
   {
      "id": "8230678162",
      "photo": "http://dummyimage.com/353x341.png/5fa2dd/ffffff",
      "guest_name": "Sherri Morales",
      "order_date": "2021-08-23 13:29:02",
      "check_in": "2021-03-18 12:22:58",
      "check_out": "2021-07-08 19:13:37",
      "request": "Epispadias",
      "room_type": "Double",
      "status": "Check in",
      "price": "€636,66",
      "amenities": "LED tv, bath, late-checkout, sea view, city tour",
      "room_imgs": [{}, {}, {}, {}],
      "room_desc": "Proin interdum mauris non ligula pellentesque ultrices. Phasellus id sapien in sapien iaculis congue. Vivamus metus arcu, adipiscing molestie, hendrerit at, vulputate vitae, nisl.\n\nAenean lectus. Pellentesque eget nunc. Donec quis orci eget orci vehicula condimentum.\n\nCurabitur in libero ut massa volutpat convallis. Morbi odio odio, elementum eu, interdum eu, tincidunt in, leo. Maecenas pulvinar lobortis est."
   },
   {
      "id": "0391335170",
      "photo": "http://dummyimage.com/256x354.png/cc0000/ffffff",
      "guest_name": "Querida Raymont",
      "order_date": "2021-10-23 07:47:14",
      "check_in": "2021-08-04 19:31:22",
      "check_out": "2021-08-30 09:20:06",
      "request": "Occ of anml-drn vehicle inj in clsn w animal being ridden",
      "room_type": "Single",
      "status": "In Progress",
      "price": "€507,12",
      "amenities": "LED tv, bath, late-checkout, sea view, city tour",
      "room_imgs": [{}, {}, {}, {}],
      "room_desc": "Donec diam neque, vestibulum eget, vulputate ut, ultrices vel, augue. Vestibulum ante ipsum primis in faucibus orci luctus et ultrices posuere cubilia Curae; Donec pharetra, magna vestibulum aliquet ultrices, erat tortor sollicitudin mi, sit amet lobortis sapien sapien non mi. Integer ac neque.\n\nDuis bibendum. Morbi non quam nec dui luctus rutrum. Nulla tellus."
   },
   {
      "id": "8422541823",
      "photo": "http://dummyimage.com/365x329.png/cc0000/ffffff",
      "guest_name": "Bathsheba Headingham",
      "order_date": "2021-04-12 06:30:59",
      "check_in": "2021-08-06 02:34:29",
      "check_out": "2021-04-24 16:52:08",
      "request": "Other non-in-line roller-skating accident, sequela",
      "room_type": "Suite",
      "status": "In Progress",
      "price": "€712,11",
      "amenities": "LED tv, bath, late-checkout, sea view, city tour",
      "room_imgs": [{}, {}, {}, {}, {}],
      "room_desc": "Aenean fermentum. Donec ut mauris eget massa tempor convallis. Nulla neque libero, convallis eget, eleifend luctus, ultricies eu, nibh.\n\nQuisque id justo sit amet sapien dignissim vestibulum. Vestibulum ante ipsum primis in faucibus orci luctus et ultrices posuere cubilia Curae; Nulla dapibus dolor vel est. Donec odio justo, sollicitudin ut, suscipit a, feugiat et, eros.\n\nVestibulum ac est lacinia nisi venenatis tristique. Fusce congue, diam id ornare imperdiet, sapien urna pretium nisl, ut volutpat sapien arcu sed augue. Aliquam erat volutpat.\n\nIn congue. Etiam justo. Etiam pretium iaculis justo."
   },
   {
      "id": "1071958127",
      "photo": "http://dummyimage.com/260x397.png/5fa2dd/ffffff",
      "guest_name": "Kevan Alwin",
      "order_date": "2021-07-09 18:13:46",
      "check_in": "2021-03-04 23:00:12",
      "check_out": "2021-09-14 06:34:05",
      "request": "Torus fracture of lower end of unspecified femur",
      "room_type": "Double Superior",
      "status": "In Progress",
      "price": "€189,96",
      "amenities": "LED tv, bath, late-checkout, sea view, city tour",
      "room_imgs": [{}, {}, {}, {}, {}],
      "room_desc": "In quis justo. Maecenas rhoncus aliquam lacus. Morbi quis tortor id nulla ultrices aliquet.\n\nMaecenas leo odio, condimentum id, luctus nec, molestie sed, justo. Pellentesque viverra pede ac diam. Cras pellentesque volutpat dui.\n\nMaecenas tristique, est et tempus semper, est quam pharetra magna, ac consequat metus sapien ut nunc. Vestibulum ante ipsum primis in faucibus orci luctus et ultrices posuere cubilia Curae; Mauris viverra diam vitae quam. Suspendisse potenti."
   },
   {
      "id": "9516032842",
      "photo": "http://dummyimage.com/375x299.png/ff4444/ffffff",
      "guest_name": "Andy Axworthy",
      "order_date": "2021-09-04 11:05:02",
      "check_in": "2021-08-09 14:14:09",
      "check_out": "2021-10-10 07:45:10",
      "request": "Nondisp unsp fx right great toe, subs for fx w malunion",
      "room_type": "Suite",
      "status": "In Progress",
      "price": "€607,45",
      "amenities": "LED tv, bath, late-checkout, sea view, city tour",
      "room_imgs": [{}, {}, {}],
      "room_desc": "Praesent id massa id nisl venenatis lacinia. Aenean sit amet justo. Morbi ut odio.\n\nCras mi pede, malesuada in, imperdiet et, commodo vulputate, justo. In blandit ultrices enim. Lorem ipsum dolor sit amet, consectetuer adipiscing elit.\n\nProin interdum mauris non ligula pellentesque ultrices. Phasellus id sapien in sapien iaculis congue. Vivamus metus arcu, adipiscing molestie, hendrerit at, vulputate vitae, nisl.\n\nAenean lectus. Pellentesque eget nunc. Donec quis orci eget orci vehicula condimentum."
   },
   {
      "id": "3719632911",
      "photo": "http://dummyimage.com/382x266.png/dddddd/000000",
      "guest_name": "Beltran Highway",
      "order_date": "2021-06-01 14:55:58",
      "check_in": "2021-02-21 17:44:33",
      "check_out": "2021-11-06 11:39:57",
      "request": "Nondisp suprcndl fx w intrcndl extn lower end r femur, init",
      "room_type": "Double",
      "status": "Check in",
      "price": "€619,55",
      "amenities": "LED tv, bath, late-checkout, sea view, city tour",
      "room_imgs": [{}, {}, {}, {}],
      "room_desc": "Nullam sit amet turpis elementum ligula vehicula consequat. Morbi a ipsum. Integer a nibh.\n\nIn quis justo. Maecenas rhoncus aliquam lacus. Morbi quis tortor id nulla ultrices aliquet.\n\nMaecenas leo odio, condimentum id, luctus nec, molestie sed, justo. Pellentesque viverra pede ac diam. Cras pellentesque volutpat dui.\n\nMaecenas tristique, est et tempus semper, est quam pharetra magna, ac consequat metus sapien ut nunc. Vestibulum ante ipsum primis in faucibus orci luctus et ultrices posuere cubilia Curae; Mauris viverra diam vitae quam. Suspendisse potenti."
   },
   {
      "id": "7705446448",
      "photo": "http://dummyimage.com/306x389.png/dddddd/000000",
      "guest_name": "Shandeigh Maddrell",
      "order_date": "2021-10-08 00:59:11",
      "check_in": "2021-03-26 14:44:24",
      "check_out": "2021-03-14 17:22:08",
      "request": "Disp fx of olecran pro w/o intartic extn unsp ulna, 7thB",
      "room_type": "Single",
      "status": "In Progress",
      "price": "€675,24",
      "amenities": "LED tv, bath, late-checkout, sea view, city tour",
      "room_imgs": [{}, {}, {}, {}, {}],
      "room_desc": "Proin leo odio, porttitor id, consequat in, consequat ut, nulla. Sed accumsan felis. Ut at dolor quis odio consequat varius.\n\nInteger ac leo. Pellentesque ultrices mattis odio. Donec vitae nisi.\n\nNam ultrices, libero non mattis pulvinar, nulla pede ullamcorper augue, a suscipit nulla elit ac nulla. Sed vel enim sit amet nunc viverra dapibus. Nulla suscipit ligula in lacus.\n\nCurabitur at ipsum ac tellus semper interdum. Mauris ullamcorper purus sit amet nulla. Quisque arcu libero, rutrum ac, lobortis vel, dapibus at, diam."
   },
   {
      "id": "1870643860",
      "photo": "http://dummyimage.com/363x381.png/dddddd/000000",
      "guest_name": "Marlowe Spittle",
      "order_date": "2021-12-18 08:56:12",
      "check_in": "2021-03-03 01:01:51",
      "check_out": "2021-07-04 18:29:02",
      "request": "Endo, nutritional and metab diseases comp preg, third tri",
      "room_type": "Single",
      "status": "In Progress",
      "price": "€623,80",
      "amenities": "LED tv, bath, late-checkout, sea view, city tour",
      "room_imgs": [{}, {}, {}, {}, {}],
      "room_desc": "Morbi non lectus. Aliquam sit amet diam in magna bibendum imperdiet. Nullam orci pede, venenatis non, sodales sed, tincidunt eu, felis.\n\nFusce posuere felis sed lacus. Morbi sem mauris, laoreet ut, rhoncus aliquet, pulvinar sed, nisl. Nunc rhoncus dui vel sem."
   },
   {
      "id": "8537616028",
      "photo": "http://dummyimage.com/399x225.png/dddddd/000000",
      "guest_name": "Clarisse Lushey",
      "order_date": "2021-03-15 18:53:58",
      "check_in": "2021-12-14 02:28:48",
      "check_out": "2021-08-08 05:47:28",
      "request": "Chronic post-traumatic headache",
      "room_type": "Double Superior",
      "status": "Check out",
      "price": "€402,01",
      "amenities": "LED tv, bath, late-checkout, sea view, city tour",
      "room_imgs": [{}, {}, {}, {}, {}],
      "room_desc": "Donec diam neque, vestibulum eget, vulputate ut, ultrices vel, augue. Vestibulum ante ipsum primis in faucibus orci luctus et ultrices posuere cubilia Curae; Donec pharetra, magna vestibulum aliquet ultrices, erat tortor sollicitudin mi, sit amet lobortis sapien sapien non mi. Integer ac neque.\n\nDuis bibendum. Morbi non quam nec dui luctus rutrum. Nulla tellus.\n\nIn sagittis dui vel nisl. Duis ac nibh. Fusce lacus purus, aliquet at, feugiat non, pretium quis, lectus.\n\nSuspendisse potenti. In eleifend quam a odio. In hac habitasse platea dictumst."
   },
   {
      "id": "0961560452",
      "photo": "http://dummyimage.com/326x288.png/ff4444/ffffff",
      "guest_name": "Rockey Prando",
      "order_date": "2021-08-12 11:31:25",
      "check_in": "2021-01-23 01:59:20",
      "check_out": "2021-05-18 20:47:25",
      "request": "Occup of special agri vehicle injured nontraf, sequela",
      "room_type": "Single",
      "status": "Check in",
      "price": "€655,83",
      "amenities": "LED tv, bath, late-checkout, sea view, city tour",
      "room_imgs": [{}, {}, {}],
      "room_desc": "Duis consequat dui nec nisi volutpat eleifend. Donec ut dolor. Morbi vel lectus in quam fringilla rhoncus.\n\nMauris enim leo, rhoncus sed, vestibulum sit amet, cursus id, turpis. Integer aliquet, massa id lobortis convallis, tortor risus dapibus augue, vel accumsan tellus nisi eu orci. Mauris lacinia sapien quis libero.\n\nNullam sit amet turpis elementum ligula vehicula consequat. Morbi a ipsum. Integer a nibh.\n\nIn quis justo. Maecenas rhoncus aliquam lacus. Morbi quis tortor id nulla ultrices aliquet."
   },
   {
      "id": "3116182337",
      "photo": "http://dummyimage.com/210x240.png/dddddd/000000",
      "guest_name": "Vasili McIleen",
      "order_date": "2021-12-27 04:29:04",
      "check_in": "2021-04-10 08:44:28",
      "check_out": "2021-12-05 12:31:09",
      "request": "Displaced fracture of coracoid process, right shoulder",
      "room_type": "Double",
      "status": "Check in",
      "price": "€445,51",
      "amenities": "LED tv, bath, late-checkout, sea view, city tour",
      "room_imgs": [{}, {}, {}, {}, {}],
      "room_desc": "Sed sagittis. Nam congue, risus semper porta volutpat, quam pede lobortis ligula, sit amet eleifend pede libero quis orci. Nullam molestie nibh in lectus.\n\nPellentesque at nulla. Suspendisse potenti. Cras in purus eu magna vulputate luctus.\n\nCum sociis natoque penatibus et magnis dis parturient montes, nascetur ridiculus mus. Vivamus vestibulum sagittis sapien. Cum sociis natoque penatibus et magnis dis parturient montes, nascetur ridiculus mus."
   },
   {
      "id": "3871501387",
      "photo": "http://dummyimage.com/355x381.png/cc0000/ffffff",
      "guest_name": "Ronny Strangman",
      "order_date": "2021-12-28 17:18:18",
      "check_in": "2021-03-12 02:57:34",
      "check_out": "2022-01-10 18:55:21",
      "request": "Insect bite (nonvenomous) of right forearm, subs encntr",
      "room_type": "Double",
      "status": "Check in",
      "price": "€727,23",
      "amenities": "LED tv, bath, late-checkout, sea view, city tour",
      "room_imgs": [{}, {}, {}, {}, {}],
      "room_desc": "Morbi non lectus. Aliquam sit amet diam in magna bibendum imperdiet. Nullam orci pede, venenatis non, sodales sed, tincidunt eu, felis.\n\nFusce posuere felis sed lacus. Morbi sem mauris, laoreet ut, rhoncus aliquet, pulvinar sed, nisl. Nunc rhoncus dui vel sem."
   },
   {
      "id": "7753099507",
      "photo": "http://dummyimage.com/395x331.png/ff4444/ffffff",
      "guest_name": "Glennis Dinwoodie",
      "order_date": "2021-02-17 08:56:12",
      "check_in": "2021-12-03 23:54:00",
      "check_out": "2021-08-05 11:39:53",
      "request": "Lac w fb of l bk wl of thorax w/o penet thoracic cavity",
      "room_type": "Double",
      "status": "In Progress",
      "price": "€507,35",
      "amenities": "LED tv, bath, late-checkout, sea view, city tour",
      "room_imgs": [{}, {}, {}],
      "room_desc": "Nulla ut erat id mauris vulputate elementum. Nullam varius. Nulla facilisi.\n\nCras non velit nec nisi vulputate nonummy. Maecenas tincidunt lacus at velit. Vivamus vel nulla eget eros elementum pellentesque."
   },
   {
      "id": "3582725448",
      "photo": "http://dummyimage.com/271x381.png/5fa2dd/ffffff",
      "guest_name": "Lila Gimlet",
      "order_date": "2021-12-14 05:30:58",
      "check_in": "2021-09-30 19:17:00",
      "check_out": "2021-07-07 05:00:57",
      "request": "Pauciarticular juvenile rheumatoid arthritis, right ank/ft",
      "room_type": "Suite",
      "status": "Check out",
      "price": "€655,01",
      "amenities": "LED tv, bath, late-checkout, sea view, city tour",
      "room_imgs": [{}, {}, {}, {}, {}],
      "room_desc": "Morbi non lectus. Aliquam sit amet diam in magna bibendum imperdiet. Nullam orci pede, venenatis non, sodales sed, tincidunt eu, felis.\n\nFusce posuere felis sed lacus. Morbi sem mauris, laoreet ut, rhoncus aliquet, pulvinar sed, nisl. Nunc rhoncus dui vel sem."
   },
   {
      "id": "9391163580",
      "photo": "http://dummyimage.com/265x314.png/dddddd/000000",
      "guest_name": "Gwennie Ridewood",
      "order_date": "2021-03-22 04:06:11",
      "check_in": "2021-06-25 15:51:17",
      "check_out": "2021-09-29 00:36:28",
      "request": "Crushed by alligator, sequela",
      "room_type": "Double",
      "status": "In Progress",
      "price": "€716,65",
      "amenities": "LED tv, bath, late-checkout, sea view, city tour",
      "room_imgs": [{}, {}, {}],
      "room_desc": "Cras non velit nec nisi vulputate nonummy. Maecenas tincidunt lacus at velit. Vivamus vel nulla eget eros elementum pellentesque.\n\nQuisque porta volutpat erat. Quisque erat eros, viverra eget, congue eget, semper rutrum, nulla. Nunc purus.\n\nPhasellus in felis. Donec semper sapien a libero. Nam dui.\n\nProin leo odio, porttitor id, consequat in, consequat ut, nulla. Sed accumsan felis. Ut at dolor quis odio consequat varius."
   },
   {
      "id": "4005957501",
      "photo": "http://dummyimage.com/290x350.png/ff4444/ffffff",
      "guest_name": "Almire Dranfield",
      "order_date": "2021-08-01 20:03:09",
      "check_in": "2021-10-30 03:05:40",
      "check_out": "2021-07-28 23:44:11",
      "request": "Heredit neuropath, NEC w diffuse mesangial prolif glomrlneph",
      "room_type": "Suite",
      "status": "In Progress",
      "price": "€536,73",
      "amenities": "LED tv, bath, late-checkout, sea view, city tour",
      "room_imgs": [{}, {}, {}, {}, {}],
      "room_desc": "Maecenas ut massa quis augue luctus tincidunt. Nulla mollis molestie lorem. Quisque ut erat.\n\nCurabitur gravida nisi at nibh. In hac habitasse platea dictumst. Aliquam augue quam, sollicitudin vitae, consectetuer eget, rutrum at, lorem.\n\nInteger tincidunt ante vel ipsum. Praesent blandit lacinia erat. Vestibulum sed magna at nunc commodo placerat.\n\nPraesent blandit. Nam nulla. Integer pede justo, lacinia eget, tincidunt eget, tempus vel, pede."
   },
   {
      "id": "0080566030",
      "photo": "http://dummyimage.com/319x275.png/ff4444/ffffff",
      "guest_name": "Luce Hagyard",
      "order_date": "2021-02-26 11:41:18",
      "check_in": "2021-05-21 10:21:44",
      "check_out": "2021-11-15 18:49:21",
      "request": "Skeletal fluorosis, left shoulder",
      "room_type": "Single",
      "status": "Check out",
      "price": "€624,58",
      "amenities": "LED tv, bath, late-checkout, sea view, city tour",
      "room_imgs": [{}, {}, {}, {}, {}],
      "room_desc": "Aenean fermentum. Donec ut mauris eget massa tempor convallis. Nulla neque libero, convallis eget, eleifend luctus, ultricies eu, nibh.\n\nQuisque id justo sit amet sapien dignissim vestibulum. Vestibulum ante ipsum primis in faucibus orci luctus et ultrices posuere cubilia Curae; Nulla dapibus dolor vel est. Donec odio justo, sollicitudin ut, suscipit a, feugiat et, eros.\n\nVestibulum ac est lacinia nisi venenatis tristique. Fusce congue, diam id ornare imperdiet, sapien urna pretium nisl, ut volutpat sapien arcu sed augue. Aliquam erat volutpat."
   },
   {
      "id": "4077698863",
      "photo": "http://dummyimage.com/293x391.png/5fa2dd/ffffff",
      "guest_name": "Cori McCoole",
      "order_date": "2021-11-20 12:18:14",
      "check_in": "2021-08-16 23:10:15",
      "check_out": "2021-11-23 06:06:23",
      "request": "Disp fx of neck of left talus, init encntr for open fracture",
      "room_type": "Double Superior",
      "status": "In Progress",
      "price": "€433,13",
      "amenities": "LED tv, bath, late-checkout, sea view, city tour",
      "room_imgs": [{}, {}, {}, {}],
      "room_desc": "Maecenas ut massa quis augue luctus tincidunt. Nulla mollis molestie lorem. Quisque ut erat.\n\nCurabitur gravida nisi at nibh. In hac habitasse platea dictumst. Aliquam augue quam, sollicitudin vitae, consectetuer eget, rutrum at, lorem.\n\nInteger tincidunt ante vel ipsum. Praesent blandit lacinia erat. Vestibulum sed magna at nunc commodo placerat.\n\nPraesent blandit. Nam nulla. Integer pede justo, lacinia eget, tincidunt eget, tempus vel, pede."
   },
   {
      "id": "6325822676",
      "photo": "http://dummyimage.com/327x335.png/cc0000/ffffff",
      "guest_name": "Luigi Giacomuzzo",
      "order_date": "2021-08-11 02:02:12",
      "check_in": "2021-01-28 02:52:14",
      "check_out": "2021-07-07 03:03:53",
      "request": "Intraop hemor/hemtom of a circ sys org comp a procedure",
      "room_type": "Suite",
      "status": "Check in",
      "price": "€387,43",
      "amenities": "LED tv, bath, late-checkout, sea view, city tour",
      "room_imgs": [{}, {}, {}, {}, {}],
      "room_desc": "Duis bibendum. Morbi non quam nec dui luctus rutrum. Nulla tellus.\n\nIn sagittis dui vel nisl. Duis ac nibh. Fusce lacus purus, aliquet at, feugiat non, pretium quis, lectus.\n\nSuspendisse potenti. In eleifend quam a odio. In hac habitasse platea dictumst.\n\nMaecenas ut massa quis augue luctus tincidunt. Nulla mollis molestie lorem. Quisque ut erat."
   },
   {
      "id": "3964396605",
      "photo": "http://dummyimage.com/330x229.png/cc0000/ffffff",
      "guest_name": "Robyn Strase",
      "order_date": "2021-04-02 02:48:15",
      "check_in": "2021-03-22 13:43:20",
      "check_out": "2021-06-13 16:40:10",
      "request": "Other dislocation of unsp ulnohumeral joint, init encntr",
      "room_type": "Suite",
      "status": "In Progress",
      "price": "€783,52",
      "amenities": "LED tv, bath, late-checkout, sea view, city tour",
      "room_imgs": [{}, {}, {}, {}],
      "room_desc": "Nullam sit amet turpis elementum ligula vehicula consequat. Morbi a ipsum. Integer a nibh.\n\nIn quis justo. Maecenas rhoncus aliquam lacus. Morbi quis tortor id nulla ultrices aliquet.\n\nMaecenas leo odio, condimentum id, luctus nec, molestie sed, justo. Pellentesque viverra pede ac diam. Cras pellentesque volutpat dui.\n\nMaecenas tristique, est et tempus semper, est quam pharetra magna, ac consequat metus sapien ut nunc. Vestibulum ante ipsum primis in faucibus orci luctus et ultrices posuere cubilia Curae; Mauris viverra diam vitae quam. Suspendisse potenti."
   },
   {
      "id": "9978478159",
      "photo": "http://dummyimage.com/394x283.png/cc0000/ffffff",
      "guest_name": "Linn Crenage",
      "order_date": "2021-07-14 04:44:43",
      "check_in": "2021-10-10 09:31:08",
      "check_out": "2021-03-06 07:33:39",
      "request": "Vesicointestinal fistula",
      "room_type": "Suite",
      "status": "Check out",
      "price": "€361,63",
      "amenities": "LED tv, bath, late-checkout, sea view, city tour",
      "room_imgs": [{}, {}, {}, {}],
      "room_desc": "Aenean lectus. Pellentesque eget nunc. Donec quis orci eget orci vehicula condimentum.\n\nCurabitur in libero ut massa volutpat convallis. Morbi odio odio, elementum eu, interdum eu, tincidunt in, leo. Maecenas pulvinar lobortis est."
   },
   {
      "id": "3909525857",
      "photo": "http://dummyimage.com/318x284.png/ff4444/ffffff",
      "guest_name": "Joyce Ivancevic",
      "order_date": "2021-09-28 08:36:11",
      "check_in": "2021-09-01 15:13:50",
      "check_out": "2021-09-03 03:10:14",
      "request": "Postthrombotic syndrome w inflammation of l low extrem",
      "room_type": "Double Superior",
      "status": "Check out",
      "price": "€565,25",
      "amenities": "LED tv, bath, late-checkout, sea view, city tour",
      "room_imgs": [{}, {}, {}],
      "room_desc": "Vestibulum ac est lacinia nisi venenatis tristique. Fusce congue, diam id ornare imperdiet, sapien urna pretium nisl, ut volutpat sapien arcu sed augue. Aliquam erat volutpat.\n\nIn congue. Etiam justo. Etiam pretium iaculis justo.\n\nIn hac habitasse platea dictumst. Etiam faucibus cursus urna. Ut tellus."
   },
   {
      "id": "0475748492",
      "photo": "http://dummyimage.com/224x238.png/5fa2dd/ffffff",
      "guest_name": "Rosana Dhennin",
      "order_date": "2021-06-05 18:23:21",
      "check_in": "2021-01-10 19:09:58",
      "check_out": "2021-02-16 21:04:09",
      "request": "Oth disp fx of upper end of r humer, subs for fx w nonunion",
      "room_type": "Suite",
      "status": "In Progress",
      "price": "€155,76",
      "amenities": "LED tv, bath, late-checkout, sea view, city tour",
      "room_imgs": [{}, {}, {}, {}],
      "room_desc": "Duis bibendum, felis sed interdum venenatis, turpis enim blandit mi, in porttitor pede justo eu massa. Donec dapibus. Duis at velit eu est congue elementum.\n\nIn hac habitasse platea dictumst. Morbi vestibulum, velit id pretium iaculis, diam erat fermentum justo, nec condimentum neque sapien placerat ante. Nulla justo."
   },
   {
      "id": "7390696230",
      "photo": "http://dummyimage.com/353x304.png/cc0000/ffffff",
      "guest_name": "Evangelina Gerauld",
      "order_date": "2021-06-29 09:52:54",
      "check_in": "2021-12-23 12:58:59",
      "check_out": "2021-10-05 07:20:13",
      "request": "Other juvenile arthritis, knee",
      "room_type": "Single",
      "status": "Check out",
      "price": "€714,92",
      "amenities": "LED tv, bath, late-checkout, sea view, city tour",
      "room_imgs": [{}, {}, {}],
      "room_desc": "Maecenas tristique, est et tempus semper, est quam pharetra magna, ac consequat metus sapien ut nunc. Vestibulum ante ipsum primis in faucibus orci luctus et ultrices posuere cubilia Curae; Mauris viverra diam vitae quam. Suspendisse potenti.\n\nNullam porttitor lacus at turpis. Donec posuere metus vitae ipsum. Aliquam non mauris."
   },
   {
      "id": "0875407951",
      "photo": "http://dummyimage.com/350x398.png/ff4444/ffffff",
      "guest_name": "Trish Ethridge",
      "order_date": "2021-01-10 05:36:38",
      "check_in": "2021-12-09 05:45:15",
      "check_out": "2021-02-15 23:52:15",
      "request": "Minor laceration of right external jugular vein, subs encntr",
      "room_type": "Double Superior",
      "status": "Check in",
      "price": "€492,94",
      "amenities": "LED tv, bath, late-checkout, sea view, city tour",
      "room_imgs": [{}, {}, {}, {}, {}],
      "room_desc": "Fusce consequat. Nulla nisl. Nunc nisl.\n\nDuis bibendum, felis sed interdum venenatis, turpis enim blandit mi, in porttitor pede justo eu massa. Donec dapibus. Duis at velit eu est congue elementum."
   },
   {
      "id": "2420295390",
      "photo": "http://dummyimage.com/257x251.png/ff4444/ffffff",
      "guest_name": "Traci Kerwen",
      "order_date": "2022-01-07 18:06:01",
      "check_in": "2021-02-19 21:23:35",
      "check_out": "2021-10-20 09:09:09",
      "request": "Postdysenteric arthropathy, left hand",
      "room_type": "Suite",
      "status": "Check out",
      "price": "€523,54",
      "amenities": "LED tv, bath, late-checkout, sea view, city tour",
      "room_imgs": [{}, {}, {}],
      "room_desc": "Proin interdum mauris non ligula pellentesque ultrices. Phasellus id sapien in sapien iaculis congue. Vivamus metus arcu, adipiscing molestie, hendrerit at, vulputate vitae, nisl.\n\nAenean lectus. Pellentesque eget nunc. Donec quis orci eget orci vehicula condimentum."
   },
   {
      "id": "2195927895",
      "photo": "http://dummyimage.com/345x225.png/5fa2dd/ffffff",
      "guest_name": "Even Hillan",
      "order_date": "2021-08-11 23:27:30",
      "check_in": "2021-07-31 04:33:17",
      "check_out": "2021-01-23 01:23:31",
      "request": "Tox eff of carb monx fr incmpl combst dmst fuel, asslt, sqla",
      "room_type": "Single",
      "status": "In Progress",
      "price": "€753,60",
      "amenities": "LED tv, bath, late-checkout, sea view, city tour",
      "room_imgs": [{}, {}, {}],
      "room_desc": "Fusce posuere felis sed lacus. Morbi sem mauris, laoreet ut, rhoncus aliquet, pulvinar sed, nisl. Nunc rhoncus dui vel sem.\n\nSed sagittis. Nam congue, risus semper porta volutpat, quam pede lobortis ligula, sit amet eleifend pede libero quis orci. Nullam molestie nibh in lectus."
   },
   {
      "id": "9439488778",
      "photo": "http://dummyimage.com/320x313.png/5fa2dd/ffffff",
      "guest_name": "Shelton Edmondson",
      "order_date": "2021-11-27 06:25:29",
      "check_in": "2021-07-20 13:09:33",
      "check_out": "2021-06-15 06:43:02",
      "request": "Underdosing of unspecified psychodysleptics, subs encntr",
      "room_type": "Double",
      "status": "In Progress",
      "price": "€252,38",
      "amenities": "LED tv, bath, late-checkout, sea view, city tour",
      "room_imgs": [{}, {}, {}, {}, {}],
      "room_desc": "Maecenas tristique, est et tempus semper, est quam pharetra magna, ac consequat metus sapien ut nunc. Vestibulum ante ipsum primis in faucibus orci luctus et ultrices posuere cubilia Curae; Mauris viverra diam vitae quam. Suspendisse potenti.\n\nNullam porttitor lacus at turpis. Donec posuere metus vitae ipsum. Aliquam non mauris.\n\nMorbi non lectus. Aliquam sit amet diam in magna bibendum imperdiet. Nullam orci pede, venenatis non, sodales sed, tincidunt eu, felis."
   },
   {
      "id": "4282925027",
      "photo": "http://dummyimage.com/362x317.png/5fa2dd/ffffff",
      "guest_name": "Percy Dorant",
      "order_date": "2021-12-03 11:05:39",
      "check_in": "2021-08-09 16:07:32",
      "check_out": "2021-07-24 06:44:57",
      "request": "Pure hypercholesterolemia",
      "room_type": "Suite",
      "status": "Check in",
      "price": "€502,77",
      "amenities": "LED tv, bath, late-checkout, sea view, city tour",
      "room_imgs": [{}, {}, {}, {}],
      "room_desc": "Nam ultrices, libero non mattis pulvinar, nulla pede ullamcorper augue, a suscipit nulla elit ac nulla. Sed vel enim sit amet nunc viverra dapibus. Nulla suscipit ligula in lacus.\n\nCurabitur at ipsum ac tellus semper interdum. Mauris ullamcorper purus sit amet nulla. Quisque arcu libero, rutrum ac, lobortis vel, dapibus at, diam."
   },
   {
      "id": "2069092720",
      "photo": "http://dummyimage.com/369x310.png/dddddd/000000",
      "guest_name": "Bride Kernock",
      "order_date": "2021-12-28 00:14:18",
      "check_in": "2021-12-23 15:43:10",
      "check_out": "2021-05-29 08:34:29",
      "request": "Poisn by antigonadtr/antiestr/antiandrg, NEC, undet, init",
      "room_type": "Double Superior",
      "status": "Check out",
      "price": "€384,93",
      "amenities": "LED tv, bath, late-checkout, sea view, city tour",
      "room_imgs": [{}, {}, {}, {}, {}],
      "room_desc": "Nulla ut erat id mauris vulputate elementum. Nullam varius. Nulla facilisi.\n\nCras non velit nec nisi vulputate nonummy. Maecenas tincidunt lacus at velit. Vivamus vel nulla eget eros elementum pellentesque.\n\nQuisque porta volutpat erat. Quisque erat eros, viverra eget, congue eget, semper rutrum, nulla. Nunc purus.\n\nPhasellus in felis. Donec semper sapien a libero. Nam dui."
   },
   {
      "id": "4657552279",
      "photo": "http://dummyimage.com/352x324.png/dddddd/000000",
      "guest_name": "Edee Oxnam",
      "order_date": "2021-09-01 00:55:21",
      "check_in": "2021-01-07 04:57:05",
      "check_out": "2021-01-20 00:55:27",
      "request": "Other chronic cystitis with hematuria",
      "room_type": "Suite",
      "status": "Check in",
      "price": "€488,65",
      "amenities": "LED tv, bath, late-checkout, sea view, city tour",
      "room_imgs": [{}, {}, {}, {}],
      "room_desc": "Pellentesque at nulla. Suspendisse potenti. Cras in purus eu magna vulputate luctus.\n\nCum sociis natoque penatibus et magnis dis parturient montes, nascetur ridiculus mus. Vivamus vestibulum sagittis sapien. Cum sociis natoque penatibus et magnis dis parturient montes, nascetur ridiculus mus.\n\nEtiam vel augue. Vestibulum rutrum rutrum neque. Aenean auctor gravida sem."
   },
   {
      "id": "3396176413",
      "photo": "http://dummyimage.com/233x394.png/ff4444/ffffff",
      "guest_name": "Janelle Curman",
      "order_date": "2021-08-01 16:59:25",
      "check_in": "2021-07-27 22:12:26",
      "check_out": "2021-09-19 16:12:44",
      "request": "Immunodeficiency associated with oth major defects",
      "room_type": "Double Superior",
      "status": "Check out",
      "price": "€115,90",
      "amenities": "LED tv, bath, late-checkout, sea view, city tour",
      "room_imgs": [{}, {}, {}, {}, {}],
      "room_desc": "Etiam vel augue. Vestibulum rutrum rutrum neque. Aenean auctor gravida sem.\n\nPraesent id massa id nisl venenatis lacinia. Aenean sit amet justo. Morbi ut odio."
   },
   {
      "id": "4226094115",
      "photo": "http://dummyimage.com/236x275.png/5fa2dd/ffffff",
      "guest_name": "Linea Molyneaux",
      "order_date": "2021-03-05 08:06:15",
      "check_in": "2021-10-06 06:48:25",
      "check_out": "2021-04-11 20:55:15",
      "request": "Unsp systemic antibiotic",
      "room_type": "Double",
      "status": "Check in",
      "price": "€139,00",
      "amenities": "LED tv, bath, late-checkout, sea view, city tour",
      "room_imgs": [{}, {}, {}, {}],
      "room_desc": "Curabitur in libero ut massa volutpat convallis. Morbi odio odio, elementum eu, interdum eu, tincidunt in, leo. Maecenas pulvinar lobortis est.\n\nPhasellus sit amet erat. Nulla tempus. Vivamus in felis eu sapien cursus vestibulum.\n\nProin eu mi. Nulla ac enim. In tempor, turpis nec euismod scelerisque, quam turpis adipiscing lorem, vitae mattis nibh ligula nec sem.\n\nDuis aliquam convallis nunc. Proin at turpis a pede posuere nonummy. Integer non velit."
   },
   {
      "id": "3420424892",
      "photo": "http://dummyimage.com/239x325.png/ff4444/ffffff",
      "guest_name": "Malissa Winder",
      "order_date": "2021-08-06 15:27:13",
      "check_in": "2021-04-16 01:46:16",
      "check_out": "2021-07-23 01:37:12",
      "request": "Delusional disorders",
      "room_type": "Single",
      "status": "Check in",
      "price": "€191,32",
      "amenities": "LED tv, bath, late-checkout, sea view, city tour",
      "room_imgs": [{}, {}, {}, {}, {}],
      "room_desc": "Integer tincidunt ante vel ipsum. Praesent blandit lacinia erat. Vestibulum sed magna at nunc commodo placerat.\n\nPraesent blandit. Nam nulla. Integer pede justo, lacinia eget, tincidunt eget, tempus vel, pede.\n\nMorbi porttitor lorem id ligula. Suspendisse ornare consequat lectus. In est risus, auctor sed, tristique in, tempus sit amet, sem.\n\nFusce consequat. Nulla nisl. Nunc nisl."
   },
   {
      "id": "1174994274",
      "photo": "http://dummyimage.com/299x297.png/5fa2dd/ffffff",
      "guest_name": "Major Milington",
      "order_date": "2021-12-27 19:31:52",
      "check_in": "2021-12-23 18:10:41",
      "check_out": "2022-01-10 08:56:30",
      "request": "Acute lacrimal canaliculitis of bilateral lacrimal passages",
      "room_type": "Double Superior",
      "status": "Check in",
      "price": "€634,99",
      "amenities": "LED tv, bath, late-checkout, sea view, city tour",
      "room_imgs": [{}, {}, {}, {}],
      "room_desc": "Proin interdum mauris non ligula pellentesque ultrices. Phasellus id sapien in sapien iaculis congue. Vivamus metus arcu, adipiscing molestie, hendrerit at, vulputate vitae, nisl.\n\nAenean lectus. Pellentesque eget nunc. Donec quis orci eget orci vehicula condimentum.\n\nCurabitur in libero ut massa volutpat convallis. Morbi odio odio, elementum eu, interdum eu, tincidunt in, leo. Maecenas pulvinar lobortis est."
   },
   {
      "id": "1441753877",
      "photo": "http://dummyimage.com/257x295.png/cc0000/ffffff",
      "guest_name": "Laird O'Carran",
      "order_date": "2021-07-23 03:24:02",
      "check_in": "2021-12-22 20:13:02",
      "check_out": "2021-12-22 18:54:45",
      "request": "Fracture of coccyx, subs encntr for fracture with nonunion",
      "room_type": "Double",
      "status": "In Progress",
      "price": "€781,41",
      "amenities": "LED tv, bath, late-checkout, sea view, city tour",
      "room_imgs": [{}, {}, {}],
      "room_desc": "Duis bibendum. Morbi non quam nec dui luctus rutrum. Nulla tellus.\n\nIn sagittis dui vel nisl. Duis ac nibh. Fusce lacus purus, aliquet at, feugiat non, pretium quis, lectus.\n\nSuspendisse potenti. In eleifend quam a odio. In hac habitasse platea dictumst."
   },
   {
      "id": "4130889133",
      "photo": "http://dummyimage.com/386x231.png/cc0000/ffffff",
      "guest_name": "Jo-ann Dunaway",
      "order_date": "2021-06-18 20:34:16",
      "check_in": "2021-04-18 13:23:16",
      "check_out": "2021-08-09 22:09:33",
      "request": "Effusion, right ankle",
      "room_type": "Single",
      "status": "Check out",
      "price": "€276,45",
      "amenities": "LED tv, bath, late-checkout, sea view, city tour",
      "room_imgs": [{}, {}, {}],
      "room_desc": "Curabitur gravida nisi at nibh. In hac habitasse platea dictumst. Aliquam augue quam, sollicitudin vitae, consectetuer eget, rutrum at, lorem.\n\nInteger tincidunt ante vel ipsum. Praesent blandit lacinia erat. Vestibulum sed magna at nunc commodo placerat.\n\nPraesent blandit. Nam nulla. Integer pede justo, lacinia eget, tincidunt eget, tempus vel, pede.\n\nMorbi porttitor lorem id ligula. Suspendisse ornare consequat lectus. In est risus, auctor sed, tristique in, tempus sit amet, sem."
   },
   {
      "id": "2895095671",
      "photo": "http://dummyimage.com/234x300.png/cc0000/ffffff",
      "guest_name": "Raddie Dradey",
      "order_date": "2021-01-04 06:36:15",
      "check_in": "2021-10-24 15:02:44",
      "check_out": "2021-08-14 03:18:40",
      "request": "Bitten by other psittacines, subsequent encounter",
      "room_type": "Single",
      "status": "Check out",
      "price": "€384,21",
      "amenities": "LED tv, bath, late-checkout, sea view, city tour",
      "room_imgs": [{}, {}, {}, {}, {}],
      "room_desc": "Maecenas tristique, est et tempus semper, est quam pharetra magna, ac consequat metus sapien ut nunc. Vestibulum ante ipsum primis in faucibus orci luctus et ultrices posuere cubilia Curae; Mauris viverra diam vitae quam. Suspendisse potenti.\n\nNullam porttitor lacus at turpis. Donec posuere metus vitae ipsum. Aliquam non mauris.\n\nMorbi non lectus. Aliquam sit amet diam in magna bibendum imperdiet. Nullam orci pede, venenatis non, sodales sed, tincidunt eu, felis.\n\nFusce posuere felis sed lacus. Morbi sem mauris, laoreet ut, rhoncus aliquet, pulvinar sed, nisl. Nunc rhoncus dui vel sem."
   },
   {
      "id": "4781124496",
      "photo": "http://dummyimage.com/312x306.png/cc0000/ffffff",
      "guest_name": "Fernanda Brommage",
      "order_date": "2021-12-07 01:21:41",
      "check_in": "2021-07-13 05:55:19",
      "check_out": "2021-01-17 18:48:26",
      "request": "Lymphocyte depleted Hodgkin lymphoma, intra-abd lymph nodes",
      "room_type": "Double Superior",
      "status": "In Progress",
      "price": "€143,30",
      "amenities": "LED tv, bath, late-checkout, sea view, city tour",
      "room_imgs": [{}, {}, {}, {}],
      "room_desc": "Integer ac leo. Pellentesque ultrices mattis odio. Donec vitae nisi.\n\nNam ultrices, libero non mattis pulvinar, nulla pede ullamcorper augue, a suscipit nulla elit ac nulla. Sed vel enim sit amet nunc viverra dapibus. Nulla suscipit ligula in lacus."
   },
   {
      "id": "7033795416",
      "photo": "http://dummyimage.com/289x368.png/dddddd/000000",
      "guest_name": "Garreth Corley",
      "order_date": "2021-04-10 11:11:44",
      "check_in": "2021-06-08 09:33:41",
      "check_out": "2021-05-27 15:58:01",
      "request": "Total retinal detachment, right eye",
      "room_type": "Suite",
      "status": "Check in",
      "price": "€339,97",
      "amenities": "LED tv, bath, late-checkout, sea view, city tour",
      "room_imgs": [{}, {}, {}, {}],
      "room_desc": "Vestibulum ac est lacinia nisi venenatis tristique. Fusce congue, diam id ornare imperdiet, sapien urna pretium nisl, ut volutpat sapien arcu sed augue. Aliquam erat volutpat.\n\nIn congue. Etiam justo. Etiam pretium iaculis justo."
   },
   {
      "id": "9094718049",
      "photo": "http://dummyimage.com/303x340.png/ff4444/ffffff",
      "guest_name": "Nahum Bolley",
      "order_date": "2021-10-15 21:49:38",
      "check_in": "2021-10-25 15:20:47",
      "check_out": "2021-01-12 22:32:00",
      "request": "Disp fx of hook process of hamate bone, unsp wrist, init",
      "room_type": "Double",
      "status": "Check out",
      "price": "€616,71",
      "amenities": "LED tv, bath, late-checkout, sea view, city tour",
      "room_imgs": [{}, {}, {}, {}, {}],
      "room_desc": "Cum sociis natoque penatibus et magnis dis parturient montes, nascetur ridiculus mus. Vivamus vestibulum sagittis sapien. Cum sociis natoque penatibus et magnis dis parturient montes, nascetur ridiculus mus.\n\nEtiam vel augue. Vestibulum rutrum rutrum neque. Aenean auctor gravida sem."
   },
   {
      "id": "1114256838",
      "photo": "http://dummyimage.com/383x251.png/dddddd/000000",
      "guest_name": "Adolphe Guilloux",
      "order_date": "2021-08-10 04:35:29",
      "check_in": "2021-07-10 07:19:46",
      "check_out": "2021-10-25 12:50:27",
      "request": "Lacerat msl/tnd lng extn msl toe at ank/ft lev, l foot, sqla",
      "room_type": "Suite",
      "status": "In Progress",
      "price": "€557,36",
      "amenities": "LED tv, bath, late-checkout, sea view, city tour",
      "room_imgs": [{}, {}, {}, {}],
      "room_desc": "Duis bibendum, felis sed interdum venenatis, turpis enim blandit mi, in porttitor pede justo eu massa. Donec dapibus. Duis at velit eu est congue elementum.\n\nIn hac habitasse platea dictumst. Morbi vestibulum, velit id pretium iaculis, diam erat fermentum justo, nec condimentum neque sapien placerat ante. Nulla justo.\n\nAliquam quis turpis eget elit sodales scelerisque. Mauris sit amet eros. Suspendisse accumsan tortor quis turpis."
   },
   {
      "id": "4450803752",
      "photo": "http://dummyimage.com/371x292.png/5fa2dd/ffffff",
      "guest_name": "Xymenes Davidofski",
      "order_date": "2021-03-09 15:28:31",
      "check_in": "2021-06-16 05:37:37",
      "check_out": "2021-11-01 00:58:48",
      "request": "Unsp open wound of left middle finger w damage to nail, init",
      "room_type": "Double",
      "status": "Check in",
      "price": "€482,09",
      "amenities": "LED tv, bath, late-checkout, sea view, city tour",
      "room_imgs": [{}, {}, {}, {}, {}],
      "room_desc": "Mauris enim leo, rhoncus sed, vestibulum sit amet, cursus id, turpis. Integer aliquet, massa id lobortis convallis, tortor risus dapibus augue, vel accumsan tellus nisi eu orci. Mauris lacinia sapien quis libero.\n\nNullam sit amet turpis elementum ligula vehicula consequat. Morbi a ipsum. Integer a nibh.\n\nIn quis justo. Maecenas rhoncus aliquam lacus. Morbi quis tortor id nulla ultrices aliquet."
   },
   {
      "id": "9788473814",
      "photo": "http://dummyimage.com/200x398.png/dddddd/000000",
      "guest_name": "Boigie Freiberg",
      "order_date": "2021-09-30 12:34:58",
      "check_in": "2021-08-04 04:01:01",
      "check_out": "2021-06-27 13:27:59",
      "request": "Nondisp commnt fx shaft of r tibia, 7thN",
      "room_type": "Single",
      "status": "In Progress",
      "price": "€643,09",
      "amenities": "LED tv, bath, late-checkout, sea view, city tour",
      "room_imgs": [{}, {}, {}, {}],
      "room_desc": "Duis aliquam convallis nunc. Proin at turpis a pede posuere nonummy. Integer non velit.\n\nDonec diam neque, vestibulum eget, vulputate ut, ultrices vel, augue. Vestibulum ante ipsum primis in faucibus orci luctus et ultrices posuere cubilia Curae; Donec pharetra, magna vestibulum aliquet ultrices, erat tortor sollicitudin mi, sit amet lobortis sapien sapien non mi. Integer ac neque.\n\nDuis bibendum. Morbi non quam nec dui luctus rutrum. Nulla tellus."
   },
   {
      "id": "5675533036",
      "photo": "http://dummyimage.com/221x242.png/ff4444/ffffff",
      "guest_name": "Niall Karchowski",
      "order_date": "2021-11-02 03:28:15",
      "check_in": "2021-06-17 21:44:47",
      "check_out": "2021-01-11 02:09:13",
      "request": "Nondisp pilon fx left tibia, subs for clos fx w routn heal",
      "room_type": "Double",
      "status": "Check out",
      "price": "€498,35",
      "amenities": "LED tv, bath, late-checkout, sea view, city tour",
      "room_imgs": [{}, {}, {}, {}, {}],
      "room_desc": "Pellentesque at nulla. Suspendisse potenti. Cras in purus eu magna vulputate luctus.\n\nCum sociis natoque penatibus et magnis dis parturient montes, nascetur ridiculus mus. Vivamus vestibulum sagittis sapien. Cum sociis natoque penatibus et magnis dis parturient montes, nascetur ridiculus mus."
   },
   {
      "id": "5145661592",
      "photo": "http://dummyimage.com/298x312.png/cc0000/ffffff",
      "guest_name": "Joy Brabon",
      "order_date": "2021-09-08 15:02:13",
      "check_in": "2021-09-03 22:58:25",
      "check_out": "2021-01-07 10:36:06",
      "request": "Toxic effect of unsp corrosive substance, self-harm",
      "room_type": "Suite",
      "status": "Check out",
      "price": "€477,36",
      "amenities": "LED tv, bath, late-checkout, sea view, city tour",
      "room_imgs": [{}, {}, {}, {}],
      "room_desc": "Quisque porta volutpat erat. Quisque erat eros, viverra eget, congue eget, semper rutrum, nulla. Nunc purus.\n\nPhasellus in felis. Donec semper sapien a libero. Nam dui."
   },
   {
      "id": "0275453863",
      "photo": "http://dummyimage.com/224x378.png/dddddd/000000",
      "guest_name": "Brockie Brunicke",
      "order_date": "2021-04-08 19:53:22",
      "check_in": "2021-07-27 13:06:31",
      "check_out": "2021-05-15 14:28:12",
      "request": "Craniofacial dysostosis",
      "room_type": "Double",
      "status": "In Progress",
      "price": "€128,17",
      "amenities": "LED tv, bath, late-checkout, sea view, city tour",
      "room_imgs": [{}, {}, {}, {}, {}],
      "room_desc": "Pellentesque at nulla. Suspendisse potenti. Cras in purus eu magna vulputate luctus.\n\nCum sociis natoque penatibus et magnis dis parturient montes, nascetur ridiculus mus. Vivamus vestibulum sagittis sapien. Cum sociis natoque penatibus et magnis dis parturient montes, nascetur ridiculus mus."
   },
   {
      "id": "7499239241",
      "photo": "http://dummyimage.com/360x313.png/5fa2dd/ffffff",
      "guest_name": "Kamila Mouan",
      "order_date": "2021-08-09 19:30:06",
      "check_in": "2021-06-04 01:58:20",
      "check_out": "2021-05-10 07:00:15",
      "request": "Malig neoplasm of lower-inner quadrant of unsp female breast",
      "room_type": "Single",
      "status": "Check out",
      "price": "€793,76",
      "amenities": "LED tv, bath, late-checkout, sea view, city tour",
      "room_imgs": [{}, {}, {}],
      "room_desc": "Mauris enim leo, rhoncus sed, vestibulum sit amet, cursus id, turpis. Integer aliquet, massa id lobortis convallis, tortor risus dapibus augue, vel accumsan tellus nisi eu orci. Mauris lacinia sapien quis libero.\n\nNullam sit amet turpis elementum ligula vehicula consequat. Morbi a ipsum. Integer a nibh.\n\nIn quis justo. Maecenas rhoncus aliquam lacus. Morbi quis tortor id nulla ultrices aliquet.\n\nMaecenas leo odio, condimentum id, luctus nec, molestie sed, justo. Pellentesque viverra pede ac diam. Cras pellentesque volutpat dui."
   },
   {
      "id": "6064948485",
      "photo": "http://dummyimage.com/366x312.png/cc0000/ffffff",
      "guest_name": "Henrieta Peto",
      "order_date": "2021-05-05 20:47:38",
      "check_in": "2021-10-06 10:43:41",
      "check_out": "2021-10-30 15:27:05",
      "request": "Unsp disp fx of surgical neck of right humerus, init",
      "room_type": "Double",
      "status": "In Progress",
      "price": "€441,30",
      "amenities": "LED tv, bath, late-checkout, sea view, city tour",
      "room_imgs": [{}, {}, {}, {}],
      "room_desc": "Integer ac leo. Pellentesque ultrices mattis odio. Donec vitae nisi.\n\nNam ultrices, libero non mattis pulvinar, nulla pede ullamcorper augue, a suscipit nulla elit ac nulla. Sed vel enim sit amet nunc viverra dapibus. Nulla suscipit ligula in lacus."
   },
   {
      "id": "4155407841",
      "photo": "http://dummyimage.com/307x235.png/ff4444/ffffff",
      "guest_name": "Brinn McReidy",
      "order_date": "2021-06-16 21:03:08",
      "check_in": "2021-02-08 08:22:03",
      "check_out": "2021-02-11 02:33:02",
      "request": "Multiple fractures of ribs, left side",
      "room_type": "Double Superior",
      "status": "Check out",
      "price": "€653,67",
      "amenities": "LED tv, bath, late-checkout, sea view, city tour",
      "room_imgs": [{}, {}, {}, {}, {}],
      "room_desc": "Phasellus in felis. Donec semper sapien a libero. Nam dui.\n\nProin leo odio, porttitor id, consequat in, consequat ut, nulla. Sed accumsan felis. Ut at dolor quis odio consequat varius."
   },
   {
      "id": "6052106158",
      "photo": "http://dummyimage.com/214x289.png/ff4444/ffffff",
      "guest_name": "Willie O'Hollegan",
      "order_date": "2021-04-05 09:35:31",
      "check_in": "2021-10-26 07:09:01",
      "check_out": "2021-05-13 04:25:08",
      "request": "Rupture of synovium, right wrist",
      "room_type": "Double",
      "status": "Check out",
      "price": "€674,52",
      "amenities": "LED tv, bath, late-checkout, sea view, city tour",
      "room_imgs": [{}, {}, {}, {}, {}],
      "room_desc": "Curabitur gravida nisi at nibh. In hac habitasse platea dictumst. Aliquam augue quam, sollicitudin vitae, consectetuer eget, rutrum at, lorem.\n\nInteger tincidunt ante vel ipsum. Praesent blandit lacinia erat. Vestibulum sed magna at nunc commodo placerat."
   },
   {
      "id": "8081324836",
      "photo": "http://dummyimage.com/328x289.png/dddddd/000000",
      "guest_name": "Jolyn Walbridge",
      "order_date": "2021-07-18 14:06:53",
      "check_in": "2021-09-07 07:12:17",
      "check_out": "2021-09-14 14:28:15",
      "request": "Complete traumatic amp of unsp lower leg, level unsp, init",
      "room_type": "Double Superior",
      "status": "In Progress",
      "price": "€725,83",
      "amenities": "LED tv, bath, late-checkout, sea view, city tour",
      "room_imgs": [{}, {}, {}, {}],
      "room_desc": "Aenean lectus. Pellentesque eget nunc. Donec quis orci eget orci vehicula condimentum.\n\nCurabitur in libero ut massa volutpat convallis. Morbi odio odio, elementum eu, interdum eu, tincidunt in, leo. Maecenas pulvinar lobortis est.\n\nPhasellus sit amet erat. Nulla tempus. Vivamus in felis eu sapien cursus vestibulum.\n\nProin eu mi. Nulla ac enim. In tempor, turpis nec euismod scelerisque, quam turpis adipiscing lorem, vitae mattis nibh ligula nec sem."
   },
   {
      "id": "4923677635",
      "photo": "http://dummyimage.com/214x378.png/ff4444/ffffff",
      "guest_name": "Rad Rohlfing",
      "order_date": "2021-08-27 20:34:39",
      "check_in": "2021-10-24 13:13:14",
      "check_out": "2021-05-27 12:37:48",
      "request": "Cholera due to Vibrio cholerae 01, biovar eltor",
      "room_type": "Double Superior",
      "status": "Check in",
      "price": "€397,43",
      "amenities": "LED tv, bath, late-checkout, sea view, city tour",
      "room_imgs": [{}, {}, {}, {}],
      "room_desc": "Aenean fermentum. Donec ut mauris eget massa tempor convallis. Nulla neque libero, convallis eget, eleifend luctus, ultricies eu, nibh.\n\nQuisque id justo sit amet sapien dignissim vestibulum. Vestibulum ante ipsum primis in faucibus orci luctus et ultrices posuere cubilia Curae; Nulla dapibus dolor vel est. Donec odio justo, sollicitudin ut, suscipit a, feugiat et, eros.\n\nVestibulum ac est lacinia nisi venenatis tristique. Fusce congue, diam id ornare imperdiet, sapien urna pretium nisl, ut volutpat sapien arcu sed augue. Aliquam erat volutpat.\n\nIn congue. Etiam justo. Etiam pretium iaculis justo."
   },
   {
      "id": "2961441595",
      "photo": "http://dummyimage.com/216x358.png/ff4444/ffffff",
      "guest_name": "Sigismond Challiner",
      "order_date": "2021-09-02 06:43:03",
      "check_in": "2021-06-06 08:18:53",
      "check_out": "2021-02-20 18:26:44",
      "request": "Infantile idiopathic scoliosis, site unspecified",
      "room_type": "Suite",
      "status": "Check in",
      "price": "€727,57",
      "amenities": "LED tv, bath, late-checkout, sea view, city tour",
      "room_imgs": [{}, {}, {}],
      "room_desc": "Aenean lectus. Pellentesque eget nunc. Donec quis orci eget orci vehicula condimentum.\n\nCurabitur in libero ut massa volutpat convallis. Morbi odio odio, elementum eu, interdum eu, tincidunt in, leo. Maecenas pulvinar lobortis est."
   },
   {
      "id": "3977334484",
      "photo": "http://dummyimage.com/261x398.png/dddddd/000000",
      "guest_name": "Bidget Worwood",
      "order_date": "2021-02-26 16:43:40",
      "check_in": "2021-07-04 22:26:54",
      "check_out": "2021-03-03 17:25:08",
      "request": "Mismatched blood in transfusion",
      "room_type": "Double Superior",
      "status": "Check out",
      "price": "€526,19",
      "amenities": "LED tv, bath, late-checkout, sea view, city tour",
      "room_imgs": [{}, {}, {}],
      "room_desc": "Quisque porta volutpat erat. Quisque erat eros, viverra eget, congue eget, semper rutrum, nulla. Nunc purus.\n\nPhasellus in felis. Donec semper sapien a libero. Nam dui.\n\nProin leo odio, porttitor id, consequat in, consequat ut, nulla. Sed accumsan felis. Ut at dolor quis odio consequat varius."
   },
   {
      "id": "7303593233",
      "photo": "http://dummyimage.com/310x373.png/5fa2dd/ffffff",
      "guest_name": "Timmie Hamberstone",
      "order_date": "2021-08-30 03:18:19",
      "check_in": "2021-08-06 20:28:03",
      "check_out": "2021-10-13 04:36:12",
      "request": "Unsp physl fx lower end of r fibula, subs for fx w nonunion",
      "room_type": "Double Superior",
      "status": "Check out",
      "price": "€647,61",
      "amenities": "LED tv, bath, late-checkout, sea view, city tour",
      "room_imgs": [{}, {}, {}, {}],
      "room_desc": "Proin interdum mauris non ligula pellentesque ultrices. Phasellus id sapien in sapien iaculis congue. Vivamus metus arcu, adipiscing molestie, hendrerit at, vulputate vitae, nisl.\n\nAenean lectus. Pellentesque eget nunc. Donec quis orci eget orci vehicula condimentum.\n\nCurabitur in libero ut massa volutpat convallis. Morbi odio odio, elementum eu, interdum eu, tincidunt in, leo. Maecenas pulvinar lobortis est."
   },
   {
      "id": "8226828376",
      "photo": "http://dummyimage.com/286x311.png/ff4444/ffffff",
      "guest_name": "Thedric Slesser",
      "order_date": "2021-01-16 14:34:16",
      "check_in": "2021-02-05 10:04:01",
      "check_out": "2021-08-01 15:52:46",
      "request": "Blister (nonthermal), left great toe, sequela",
      "room_type": "Double Superior",
      "status": "In Progress",
      "price": "€143,06",
      "amenities": "LED tv, bath, late-checkout, sea view, city tour",
      "room_imgs": [{}, {}, {}],
      "room_desc": "Aenean lectus. Pellentesque eget nunc. Donec quis orci eget orci vehicula condimentum.\n\nCurabitur in libero ut massa volutpat convallis. Morbi odio odio, elementum eu, interdum eu, tincidunt in, leo. Maecenas pulvinar lobortis est.\n\nPhasellus sit amet erat. Nulla tempus. Vivamus in felis eu sapien cursus vestibulum.\n\nProin eu mi. Nulla ac enim. In tempor, turpis nec euismod scelerisque, quam turpis adipiscing lorem, vitae mattis nibh ligula nec sem."
   },
   {
      "id": "1335641505",
      "photo": "http://dummyimage.com/351x383.png/cc0000/ffffff",
      "guest_name": "Trenna Westmarland",
      "order_date": "2021-05-12 17:19:32",
      "check_in": "2021-04-05 19:01:02",
      "check_out": "2021-04-27 02:51:27",
      "request": "Unspecified injury of external genitals, initial encounter",
      "room_type": "Double Superior",
      "status": "Check in",
      "price": "€239,34",
      "amenities": "LED tv, bath, late-checkout, sea view, city tour",
      "room_imgs": [{}, {}, {}, {}],
      "room_desc": "Integer ac leo. Pellentesque ultrices mattis odio. Donec vitae nisi.\n\nNam ultrices, libero non mattis pulvinar, nulla pede ullamcorper augue, a suscipit nulla elit ac nulla. Sed vel enim sit amet nunc viverra dapibus. Nulla suscipit ligula in lacus.\n\nCurabitur at ipsum ac tellus semper interdum. Mauris ullamcorper purus sit amet nulla. Quisque arcu libero, rutrum ac, lobortis vel, dapibus at, diam."
   },
   {
      "id": "8082444940",
      "photo": "http://dummyimage.com/327x286.png/5fa2dd/ffffff",
      "guest_name": "Marisa Iorns",
      "order_date": "2021-11-22 13:12:34",
      "check_in": "2021-12-07 22:44:42",
      "check_out": "2021-11-16 04:29:08",
      "request": "Poisoning by propionic acid derivatives, self-harm, subs",
      "room_type": "Single",
      "status": "Check in",
      "price": "€700,68",
      "amenities": "LED tv, bath, late-checkout, sea view, city tour",
      "room_imgs": [{}, {}, {}, {}, {}],
      "room_desc": "Cum sociis natoque penatibus et magnis dis parturient montes, nascetur ridiculus mus. Vivamus vestibulum sagittis sapien. Cum sociis natoque penatibus et magnis dis parturient montes, nascetur ridiculus mus.\n\nEtiam vel augue. Vestibulum rutrum rutrum neque. Aenean auctor gravida sem."
   },
   {
      "id": "3646103094",
      "photo": "http://dummyimage.com/386x304.png/cc0000/ffffff",
      "guest_name": "Shadow Pretsel",
      "order_date": "2021-09-04 10:49:35",
      "check_in": "2021-09-27 16:10:11",
      "check_out": "2021-01-30 22:04:44",
      "request": "Nondisp fx of med condyle of r tibia, 7thN",
      "room_type": "Suite",
      "status": "In Progress",
      "price": "€651,99",
      "amenities": "LED tv, bath, late-checkout, sea view, city tour",
      "room_imgs": [{}, {}, {}, {}],
      "room_desc": "Suspendisse potenti. In eleifend quam a odio. In hac habitasse platea dictumst.\n\nMaecenas ut massa quis augue luctus tincidunt. Nulla mollis molestie lorem. Quisque ut erat.\n\nCurabitur gravida nisi at nibh. In hac habitasse platea dictumst. Aliquam augue quam, sollicitudin vitae, consectetuer eget, rutrum at, lorem."
   },
   {
      "id": "1911673513",
      "photo": "http://dummyimage.com/361x302.png/5fa2dd/ffffff",
      "guest_name": "Cynthie Huckell",
      "order_date": "2021-08-01 17:32:56",
      "check_in": "2021-10-26 06:53:58",
      "check_out": "2021-01-29 08:34:14",
      "request": "Poisoning by smallpox vaccines, accidental, subs",
      "room_type": "Double",
      "status": "Check in",
      "price": "€222,38",
      "amenities": "LED tv, bath, late-checkout, sea view, city tour",
      "room_imgs": [{}, {}, {}],
      "room_desc": "In sagittis dui vel nisl. Duis ac nibh. Fusce lacus purus, aliquet at, feugiat non, pretium quis, lectus.\n\nSuspendisse potenti. In eleifend quam a odio. In hac habitasse platea dictumst.\n\nMaecenas ut massa quis augue luctus tincidunt. Nulla mollis molestie lorem. Quisque ut erat."
   },
   {
      "id": "1992237417",
      "photo": "http://dummyimage.com/274x365.png/ff4444/ffffff",
      "guest_name": "Stacey Youson",
      "order_date": "2021-09-03 06:37:57",
      "check_in": "2021-10-13 10:37:46",
      "check_out": "2021-09-30 02:13:01",
      "request": "Unspecified fracture of third metacarpal bone, left hand",
      "room_type": "Suite",
      "status": "In Progress",
      "price": "€690,42",
      "amenities": "LED tv, bath, late-checkout, sea view, city tour",
      "room_imgs": [{}, {}, {}, {}],
      "room_desc": "Sed sagittis. Nam congue, risus semper porta volutpat, quam pede lobortis ligula, sit amet eleifend pede libero quis orci. Nullam molestie nibh in lectus.\n\nPellentesque at nulla. Suspendisse potenti. Cras in purus eu magna vulputate luctus."
   },
   {
      "id": "8838206627",
      "photo": "http://dummyimage.com/389x346.png/dddddd/000000",
      "guest_name": "Othello Cunniam",
      "order_date": "2022-01-07 16:47:00",
      "check_in": "2021-06-07 22:40:24",
      "check_out": "2021-10-31 23:00:44",
      "request": "Other skateboard accident",
      "room_type": "Double Superior",
      "status": "In Progress",
      "price": "€108,75",
      "amenities": "LED tv, bath, late-checkout, sea view, city tour",
      "room_imgs": [{}, {}, {}],
      "room_desc": "Suspendisse potenti. In eleifend quam a odio. In hac habitasse platea dictumst.\n\nMaecenas ut massa quis augue luctus tincidunt. Nulla mollis molestie lorem. Quisque ut erat.\n\nCurabitur gravida nisi at nibh. In hac habitasse platea dictumst. Aliquam augue quam, sollicitudin vitae, consectetuer eget, rutrum at, lorem."
   },
   {
      "id": "4233416025",
      "photo": "http://dummyimage.com/242x233.png/dddddd/000000",
      "guest_name": "Kristan Alexandre",
      "order_date": "2021-11-16 09:40:37",
      "check_in": "2021-02-15 06:13:23",
      "check_out": "2021-04-12 21:11:48",
      "request": "Rheumatoid nodule, shoulder",
      "room_type": "Double Superior",
      "status": "Check in",
      "price": "€743,04",
      "amenities": "LED tv, bath, late-checkout, sea view, city tour",
      "room_imgs": [{}, {}, {}, {}, {}],
      "room_desc": "Praesent id massa id nisl venenatis lacinia. Aenean sit amet justo. Morbi ut odio.\n\nCras mi pede, malesuada in, imperdiet et, commodo vulputate, justo. In blandit ultrices enim. Lorem ipsum dolor sit amet, consectetuer adipiscing elit.\n\nProin interdum mauris non ligula pellentesque ultrices. Phasellus id sapien in sapien iaculis congue. Vivamus metus arcu, adipiscing molestie, hendrerit at, vulputate vitae, nisl.\n\nAenean lectus. Pellentesque eget nunc. Donec quis orci eget orci vehicula condimentum."
   },
   {
      "id": "3369007193",
      "photo": "http://dummyimage.com/384x296.png/dddddd/000000",
      "guest_name": "Truda Treske",
      "order_date": "2021-01-06 00:27:20",
      "check_in": "2021-12-07 06:25:17",
      "check_out": "2021-01-29 03:33:08",
      "request": "Squamous cell carcinoma skin/ left eyelid, including canthus",
      "room_type": "Single",
      "status": "Check in",
      "price": "€443,72",
      "amenities": "LED tv, bath, late-checkout, sea view, city tour",
      "room_imgs": [{}, {}, {}],
      "room_desc": "Fusce consequat. Nulla nisl. Nunc nisl.\n\nDuis bibendum, felis sed interdum venenatis, turpis enim blandit mi, in porttitor pede justo eu massa. Donec dapibus. Duis at velit eu est congue elementum.\n\nIn hac habitasse platea dictumst. Morbi vestibulum, velit id pretium iaculis, diam erat fermentum justo, nec condimentum neque sapien placerat ante. Nulla justo."
   },
   {
      "id": "6243228258",
      "photo": "http://dummyimage.com/381x254.png/cc0000/ffffff",
      "guest_name": "Alvie Pryor",
      "order_date": "2021-12-12 23:30:38",
      "check_in": "2021-11-13 19:20:12",
      "check_out": "2021-02-26 06:44:00",
      "request": "Failed attempt vaginal birth after previous cesarean del",
      "room_type": "Single",
      "status": "Check in",
      "price": "€444,87",
      "amenities": "LED tv, bath, late-checkout, sea view, city tour",
      "room_imgs": [{}, {}, {}],
      "room_desc": "Vestibulum ac est lacinia nisi venenatis tristique. Fusce congue, diam id ornare imperdiet, sapien urna pretium nisl, ut volutpat sapien arcu sed augue. Aliquam erat volutpat.\n\nIn congue. Etiam justo. Etiam pretium iaculis justo.\n\nIn hac habitasse platea dictumst. Etiam faucibus cursus urna. Ut tellus."
   },
   {
      "id": "0720760879",
      "photo": "http://dummyimage.com/355x321.png/dddddd/000000",
      "guest_name": "Betty Poate",
      "order_date": "2021-01-12 15:49:48",
      "check_in": "2021-05-19 03:03:41",
      "check_out": "2021-06-28 03:27:35",
      "request": "Occupant of rail trn/veh injured in transport accident",
      "room_type": "Double",
      "status": "Check out",
      "price": "€487,21",
      "amenities": "LED tv, bath, late-checkout, sea view, city tour",
      "room_imgs": [{}, {}, {}],
      "room_desc": "Cras non velit nec nisi vulputate nonummy. Maecenas tincidunt lacus at velit. Vivamus vel nulla eget eros elementum pellentesque.\n\nQuisque porta volutpat erat. Quisque erat eros, viverra eget, congue eget, semper rutrum, nulla. Nunc purus."
   },
   {
      "id": "9256752956",
      "photo": "http://dummyimage.com/335x293.png/cc0000/ffffff",
      "guest_name": "Dru Neeson",
      "order_date": "2021-11-16 20:56:12",
      "check_in": "2021-05-28 00:15:32",
      "check_out": "2021-06-05 11:22:15",
      "request": "Loose body in unspecified wrist",
      "room_type": "Double",
      "status": "Check out",
      "price": "€373,22",
      "amenities": "LED tv, bath, late-checkout, sea view, city tour",
      "room_imgs": [{}, {}, {}, {}, {}],
      "room_desc": "Maecenas leo odio, condimentum id, luctus nec, molestie sed, justo. Pellentesque viverra pede ac diam. Cras pellentesque volutpat dui.\n\nMaecenas tristique, est et tempus semper, est quam pharetra magna, ac consequat metus sapien ut nunc. Vestibulum ante ipsum primis in faucibus orci luctus et ultrices posuere cubilia Curae; Mauris viverra diam vitae quam. Suspendisse potenti."
   },
   {
      "id": "0416374042",
      "photo": "http://dummyimage.com/350x311.png/ff4444/ffffff",
      "guest_name": "Ambros Braghini",
      "order_date": "2021-09-30 02:21:12",
      "check_in": "2021-08-15 17:37:07",
      "check_out": "2021-11-12 12:27:18",
      "request": "Complications of gastric band procedure",
      "room_type": "Double Superior",
      "status": "In Progress",
      "price": "€797,19",
      "amenities": "LED tv, bath, late-checkout, sea view, city tour",
      "room_imgs": [{}, {}, {}],
      "room_desc": "Nulla ut erat id mauris vulputate elementum. Nullam varius. Nulla facilisi.\n\nCras non velit nec nisi vulputate nonummy. Maecenas tincidunt lacus at velit. Vivamus vel nulla eget eros elementum pellentesque."
   },
   {
      "id": "5878801876",
      "photo": "http://dummyimage.com/327x273.png/cc0000/ffffff",
      "guest_name": "Romola Giuron",
      "order_date": "2021-09-04 02:32:37",
      "check_in": "2021-04-28 13:44:32",
      "check_out": "2021-08-06 07:17:13",
      "request": "Superficial foreign body, right great toe, sequela",
      "room_type": "Double Superior",
      "status": "Check in",
      "price": "€406,44",
      "amenities": "LED tv, bath, late-checkout, sea view, city tour",
      "room_imgs": [{}, {}, {}],
      "room_desc": "Nullam porttitor lacus at turpis. Donec posuere metus vitae ipsum. Aliquam non mauris.\n\nMorbi non lectus. Aliquam sit amet diam in magna bibendum imperdiet. Nullam orci pede, venenatis non, sodales sed, tincidunt eu, felis."
   },
   {
      "id": "4772230149",
      "photo": "http://dummyimage.com/333x225.png/dddddd/000000",
      "guest_name": "Adolphe Husher",
      "order_date": "2021-02-12 16:54:21",
      "check_in": "2021-12-15 17:52:30",
      "check_out": "2021-12-21 14:17:56",
      "request": "Oth osteopor w crnt path fx, verteb, subs for fx w malunion",
      "room_type": "Double Superior",
      "status": "Check out",
      "price": "€500,41",
      "amenities": "LED tv, bath, late-checkout, sea view, city tour",
      "room_imgs": [{}, {}, {}],
      "room_desc": "Duis aliquam convallis nunc. Proin at turpis a pede posuere nonummy. Integer non velit.\n\nDonec diam neque, vestibulum eget, vulputate ut, ultrices vel, augue. Vestibulum ante ipsum primis in faucibus orci luctus et ultrices posuere cubilia Curae; Donec pharetra, magna vestibulum aliquet ultrices, erat tortor sollicitudin mi, sit amet lobortis sapien sapien non mi. Integer ac neque.\n\nDuis bibendum. Morbi non quam nec dui luctus rutrum. Nulla tellus."
   },
   {
      "id": "0565458078",
      "photo": "http://dummyimage.com/345x391.png/ff4444/ffffff",
      "guest_name": "Ad Rishworth",
      "order_date": "2021-04-19 11:00:11",
      "check_in": "2021-02-12 15:00:59",
      "check_out": "2021-11-27 14:10:04",
      "request": "Athscl type of bypass graft(s) of the left leg w ulceration",
      "room_type": "Suite",
      "status": "In Progress",
      "price": "€286,77",
      "amenities": "LED tv, bath, late-checkout, sea view, city tour",
      "room_imgs": [{}, {}, {}],
      "room_desc": "Duis consequat dui nec nisi volutpat eleifend. Donec ut dolor. Morbi vel lectus in quam fringilla rhoncus.\n\nMauris enim leo, rhoncus sed, vestibulum sit amet, cursus id, turpis. Integer aliquet, massa id lobortis convallis, tortor risus dapibus augue, vel accumsan tellus nisi eu orci. Mauris lacinia sapien quis libero.\n\nNullam sit amet turpis elementum ligula vehicula consequat. Morbi a ipsum. Integer a nibh."
   },
   {
      "id": "4076916484",
      "photo": "http://dummyimage.com/389x323.png/5fa2dd/ffffff",
      "guest_name": "Randal Trenaman",
      "order_date": "2021-07-02 19:42:48",
      "check_in": "2021-10-17 16:46:05",
      "check_out": "2021-08-01 18:23:14",
      "request": "Unsp inj long flexor musc/fasc/tend l thm at wrs/hnd lv",
      "room_type": "Suite",
      "status": "Check out",
      "price": "€264,52",
      "amenities": "LED tv, bath, late-checkout, sea view, city tour",
      "room_imgs": [{}, {}, {}],
      "room_desc": "Morbi non lectus. Aliquam sit amet diam in magna bibendum imperdiet. Nullam orci pede, venenatis non, sodales sed, tincidunt eu, felis.\n\nFusce posuere felis sed lacus. Morbi sem mauris, laoreet ut, rhoncus aliquet, pulvinar sed, nisl. Nunc rhoncus dui vel sem."
   }
]
